{
    "FlowSamples" : 
    {
        "Type" : "Folder",

        "Job3": {
            "Type" : "Job:Command",
            "Comment" : "Nahuel tests",
            "Command" : "echo 'Job3, primero del Flow, carpeta tipo Folder (SmartFolder)'",
            "RunAs" : "workbench"  
        },
        "Job4": {
            "Type": "Job:Command",
            "Comment" : "Nahuel tests",
            "Command" : "echo 'Job4, segundo del Flow, carpeta tipo Folder (SmartFolder)'",
            "RunAs": "workbench"
        },
        "flow1": {
            "Type": "Flow",
            "Sequence": ["Job3", "Job4"]
        }
}
}

